{
  "arm64":{
    "className":"__NSConcreteURLComponents",
    "ivars":[
      {
        "alignment":0,
        "ivarType":"int",
        "name":"_lock",
        "offset":8,
        "size":0,
        "type":"ivar"
      },
      {
        "alignment":0,
        "ivarType":"NSString *",
        "name":"_urlString",
        "offset":16,
        "size":0,
        "type":"ivar"
      },
      {
        "alignment":0,
        "ivarType":"struct _URIParseInfo",
        "name":"_parseInfo",
        "offset":24,
        "size":0,
        "type":"ivar"
      },
      {
        "alignment":0,
        "ivarType":"unsigned int :1",
        "name":"_schemeComponentValid",
        "offset":104,
        "size":0,
        "type":"ivar"
      },
      {
        "alignment":0,
        "ivarType":"unsigned int :1",
        "name":"_userComponentValid",
        "offset":104,
        "size":0,
        "type":"ivar"
      },
      {
        "alignment":0,
        "ivarType":"unsigned int :1",
        "name":"_passwordComponentValid",
        "offset":104,
        "size":0,
        "type":"ivar"
      },
      {
        "alignment":0,
        "ivarType":"unsigned int :1",
        "name":"_hostComponentValid",
        "offset":104,
        "size":0,
        "type":"ivar"
      },
      {
        "alignment":0,
        "ivarType":"unsigned int :1",
        "name":"_portComponentValid",
        "offset":104,
        "size":0,
        "type":"ivar"
      },
      {
        "alignment":0,
        "ivarType":"unsigned int :1",
        "name":"_pathComponentValid",
        "offset":104,
        "size":0,
        "type":"ivar"
      },
      {
        "alignment":0,
        "ivarType":"unsigned int :1",
        "name":"_queryComponentValid",
        "offset":104,
        "size":0,
        "type":"ivar"
      },
      {
        "alignment":0,
        "ivarType":"unsigned int :1",
        "name":"_fragmentComponentValid",
        "offset":104,
        "size":0,
        "type":"ivar"
      },
      {
        "alignment":0,
        "ivarType":"NSString *",
        "name":"_schemeComponent",
        "offset":112,
        "size":0,
        "type":"ivar"
      },
      {
        "alignment":0,
        "ivarType":"NSString *",
        "name":"_userComponent",
        "offset":120,
        "size":0,
        "type":"ivar"
      },
      {
        "alignment":0,
        "ivarType":"NSString *",
        "name":"_passwordComponent",
        "offset":128,
        "size":0,
        "type":"ivar"
      },
      {
        "alignment":0,
        "ivarType":"NSString *",
        "name":"_hostComponent",
        "offset":136,
        "size":0,
        "type":"ivar"
      },
      {
        "alignment":0,
        "ivarType":"NSNumber *",
        "name":"_portComponent",
        "offset":144,
        "size":0,
        "type":"ivar"
      },
      {
        "alignment":0,
        "ivarType":"NSString *",
        "name":"_pathComponent",
        "offset":152,
        "size":0,
        "type":"ivar"
      },
      {
        "alignment":0,
        "ivarType":"NSString *",
        "name":"_queryComponent",
        "offset":160,
        "size":0,
        "type":"ivar"
      },
      {
        "alignment":0,
        "ivarType":"NSString *",
        "name":"_fragmentComponent",
        "offset":168,
        "size":0,
        "type":"ivar"
      }
    ],
    "superClassName":"NSURLComponents",
    "type":"class"
  },
  "armv7":{
    "className":"__NSConcreteURLComponents",
    "ivars":[
      {
        "alignment":0,
        "ivarType":"int",
        "name":"_lock",
        "offset":4,
        "size":0,
        "type":"ivar"
      },
      {
        "alignment":0,
        "ivarType":"NSString *",
        "name":"_urlString",
        "offset":8,
        "size":0,
        "type":"ivar"
      },
      {
        "alignment":0,
        "ivarType":"struct _URIParseInfo",
        "name":"_parseInfo",
        "offset":12,
        "size":0,
        "type":"ivar"
      },
      {
        "alignment":0,
        "ivarType":"unsigned int :1",
        "name":"_schemeComponentValid",
        "offset":52,
        "size":0,
        "type":"ivar"
      },
      {
        "alignment":0,
        "ivarType":"unsigned int :1",
        "name":"_userComponentValid",
        "offset":52,
        "size":0,
        "type":"ivar"
      },
      {
        "alignment":0,
        "ivarType":"unsigned int :1",
        "name":"_passwordComponentValid",
        "offset":52,
        "size":0,
        "type":"ivar"
      },
      {
        "alignment":0,
        "ivarType":"unsigned int :1",
        "name":"_hostComponentValid",
        "offset":52,
        "size":0,
        "type":"ivar"
      },
      {
        "alignment":0,
        "ivarType":"unsigned int :1",
        "name":"_portComponentValid",
        "offset":52,
        "size":0,
        "type":"ivar"
      },
      {
        "alignment":0,
        "ivarType":"unsigned int :1",
        "name":"_pathComponentValid",
        "offset":52,
        "size":0,
        "type":"ivar"
      },
      {
        "alignment":0,
        "ivarType":"unsigned int :1",
        "name":"_queryComponentValid",
        "offset":52,
        "size":0,
        "type":"ivar"
      },
      {
        "alignment":0,
        "ivarType":"unsigned int :1",
        "name":"_fragmentComponentValid",
        "offset":52,
        "size":0,
        "type":"ivar"
      },
      {
        "alignment":0,
        "ivarType":"NSString *",
        "name":"_schemeComponent",
        "offset":56,
        "size":0,
        "type":"ivar"
      },
      {
        "alignment":0,
        "ivarType":"NSString *",
        "name":"_userComponent",
        "offset":60,
        "size":0,
        "type":"ivar"
      },
      {
        "alignment":0,
        "ivarType":"NSString *",
        "name":"_passwordComponent",
        "offset":64,
        "size":0,
        "type":"ivar"
      },
      {
        "alignment":0,
        "ivarType":"NSString *",
        "name":"_hostComponent",
        "offset":68,
        "size":0,
        "type":"ivar"
      },
      {
        "alignment":0,
        "ivarType":"NSNumber *",
        "name":"_portComponent",
        "offset":72,
        "size":0,
        "type":"ivar"
      },
      {
        "alignment":0,
        "ivarType":"NSString *",
        "name":"_pathComponent",
        "offset":76,
        "size":0,
        "type":"ivar"
      },
      {
        "alignment":0,
        "ivarType":"NSString *",
        "name":"_queryComponent",
        "offset":80,
        "size":0,
        "type":"ivar"
      },
      {
        "alignment":0,
        "ivarType":"NSString *",
        "name":"_fragmentComponent",
        "offset":84,
        "size":0,
        "type":"ivar"
      }
    ],
    "superClassName":"NSURLComponents",
    "type":"class"
  },
  "i386":{
    "className":"__NSConcreteURLComponents",
    "ivars":[
      {
        "alignment":0,
        "ivarType":"int",
        "name":"_lock",
        "offset":4,
        "size":0,
        "type":"ivar"
      },
      {
        "alignment":0,
        "ivarType":"NSString *",
        "name":"_urlString",
        "offset":8,
        "size":0,
        "type":"ivar"
      },
      {
        "alignment":0,
        "ivarType":"struct _URIParseInfo",
        "name":"_parseInfo",
        "offset":12,
        "size":0,
        "type":"ivar"
      },
      {
        "alignment":0,
        "ivarType":"unsigned int :1",
        "name":"_schemeComponentValid",
        "offset":52,
        "size":0,
        "type":"ivar"
      },
      {
        "alignment":0,
        "ivarType":"unsigned int :1",
        "name":"_userComponentValid",
        "offset":52,
        "size":0,
        "type":"ivar"
      },
      {
        "alignment":0,
        "ivarType":"unsigned int :1",
        "name":"_passwordComponentValid",
        "offset":52,
        "size":0,
        "type":"ivar"
      },
      {
        "alignment":0,
        "ivarType":"unsigned int :1",
        "name":"_hostComponentValid",
        "offset":52,
        "size":0,
        "type":"ivar"
      },
      {
        "alignment":0,
        "ivarType":"unsigned int :1",
        "name":"_portComponentValid",
        "offset":52,
        "size":0,
        "type":"ivar"
      },
      {
        "alignment":0,
        "ivarType":"unsigned int :1",
        "name":"_pathComponentValid",
        "offset":52,
        "size":0,
        "type":"ivar"
      },
      {
        "alignment":0,
        "ivarType":"unsigned int :1",
        "name":"_queryComponentValid",
        "offset":52,
        "size":0,
        "type":"ivar"
      },
      {
        "alignment":0,
        "ivarType":"unsigned int :1",
        "name":"_fragmentComponentValid",
        "offset":52,
        "size":0,
        "type":"ivar"
      },
      {
        "alignment":0,
        "ivarType":"NSString *",
        "name":"_schemeComponent",
        "offset":56,
        "size":0,
        "type":"ivar"
      },
      {
        "alignment":0,
        "ivarType":"NSString *",
        "name":"_userComponent",
        "offset":60,
        "size":0,
        "type":"ivar"
      },
      {
        "alignment":0,
        "ivarType":"NSString *",
        "name":"_passwordComponent",
        "offset":64,
        "size":0,
        "type":"ivar"
      },
      {
        "alignment":0,
        "ivarType":"NSString *",
        "name":"_hostComponent",
        "offset":68,
        "size":0,
        "type":"ivar"
      },
      {
        "alignment":0,
        "ivarType":"NSNumber *",
        "name":"_portComponent",
        "offset":72,
        "size":0,
        "type":"ivar"
      },
      {
        "alignment":0,
        "ivarType":"NSString *",
        "name":"_pathComponent",
        "offset":76,
        "size":0,
        "type":"ivar"
      },
      {
        "alignment":0,
        "ivarType":"NSString *",
        "name":"_queryComponent",
        "offset":80,
        "size":0,
        "type":"ivar"
      },
      {
        "alignment":0,
        "ivarType":"NSString *",
        "name":"_fragmentComponent",
        "offset":84,
        "size":0,
        "type":"ivar"
      }
    ],
    "superClassName":"NSURLComponents",
    "type":"class"
  },
  "x86_64":{
    "className":"__NSConcreteURLComponents",
    "ivars":[
      {
        "alignment":0,
        "ivarType":"int",
        "name":"_lock",
        "offset":8,
        "size":0,
        "type":"ivar"
      },
      {
        "alignment":0,
        "ivarType":"NSString *",
        "name":"_urlString",
        "offset":16,
        "size":0,
        "type":"ivar"
      },
      {
        "alignment":0,
        "ivarType":"struct _URIParseInfo",
        "name":"_parseInfo",
        "offset":24,
        "size":0,
        "type":"ivar"
      },
      {
        "alignment":0,
        "ivarType":"unsigned int :1",
        "name":"_schemeComponentValid",
        "offset":104,
        "size":0,
        "type":"ivar"
      },
      {
        "alignment":0,
        "ivarType":"unsigned int :1",
        "name":"_userComponentValid",
        "offset":104,
        "size":0,
        "type":"ivar"
      },
      {
        "alignment":0,
        "ivarType":"unsigned int :1",
        "name":"_passwordComponentValid",
        "offset":104,
        "size":0,
        "type":"ivar"
      },
      {
        "alignment":0,
        "ivarType":"unsigned int :1",
        "name":"_hostComponentValid",
        "offset":104,
        "size":0,
        "type":"ivar"
      },
      {
        "alignment":0,
        "ivarType":"unsigned int :1",
        "name":"_portComponentValid",
        "offset":104,
        "size":0,
        "type":"ivar"
      },
      {
        "alignment":0,
        "ivarType":"unsigned int :1",
        "name":"_pathComponentValid",
        "offset":104,
        "size":0,
        "type":"ivar"
      },
      {
        "alignment":0,
        "ivarType":"unsigned int :1",
        "name":"_queryComponentValid",
        "offset":104,
        "size":0,
        "type":"ivar"
      },
      {
        "alignment":0,
        "ivarType":"unsigned int :1",
        "name":"_fragmentComponentValid",
        "offset":104,
        "size":0,
        "type":"ivar"
      },
      {
        "alignment":0,
        "ivarType":"NSString *",
        "name":"_schemeComponent",
        "offset":112,
        "size":0,
        "type":"ivar"
      },
      {
        "alignment":0,
        "ivarType":"NSString *",
        "name":"_userComponent",
        "offset":120,
        "size":0,
        "type":"ivar"
      },
      {
        "alignment":0,
        "ivarType":"NSString *",
        "name":"_passwordComponent",
        "offset":128,
        "size":0,
        "type":"ivar"
      },
      {
        "alignment":0,
        "ivarType":"NSString *",
        "name":"_hostComponent",
        "offset":136,
        "size":0,
        "type":"ivar"
      },
      {
        "alignment":0,
        "ivarType":"NSNumber *",
        "name":"_portComponent",
        "offset":144,
        "size":0,
        "type":"ivar"
      },
      {
        "alignment":0,
        "ivarType":"NSString *",
        "name":"_pathComponent",
        "offset":152,
        "size":0,
        "type":"ivar"
      },
      {
        "alignment":0,
        "ivarType":"NSString *",
        "name":"_queryComponent",
        "offset":160,
        "size":0,
        "type":"ivar"
      },
      {
        "alignment":0,
        "ivarType":"NSString *",
        "name":"_fragmentComponent",
        "offset":168,
        "size":0,
        "type":"ivar"
      }
    ],
    "superClassName":"NSURLComponents",
    "type":"class"
  }
}